json_tricks/__init__.py
json_tricks/_version.py
json_tricks/comment.py
json_tricks/decoders.py
json_tricks/encoders.py
json_tricks/nonp.py
json_tricks/np.py
json_tricks/np_utils.py
json_tricks/utils.py
json_tricks-3.17.3.dist-info/LICENSE.txt
json_tricks-3.17.3.dist-info/METADATA
json_tricks-3.17.3.dist-info/WHEEL
json_tricks-3.17.3.dist-info/top_level.txt
json_tricks-3.17.3.dist-info/zip-safe
json_tricks-3.17.3.dist-info/RECORD
