Metadata-Version: 2.1
Name: json_tricks
Version: 3.17.3
Summary: Extra features for Python's JSON: comments, order, numpy, pandas, datetimes, and many more! Simple but customizable.
Home-page: https://github.com/mverleg/pyjson_tricks
Author: Mark V
Author-email: markv.nl.dev@gmail.com
Maintainer: Mark V
License: Revised BSD License (LICENSE.txt)
Keywords: json,numpy,OrderedDict,comments,pandas,pytz,enum,encode,decode,serialize,deserialize
Platform: UNKNOWN
Classifier: Development Status :: 5 - Production/Stable
Classifier: Development Status :: 6 - Mature
Classifier: Intended Audience :: Developers
Classifier: Natural Language :: English
Classifier: License :: OSI Approved :: BSD License
Classifier: Operating System :: OS Independent
Classifier: Programming Language :: Python
Classifier: Programming Language :: Python :: 2
Classifier: Programming Language :: Python :: 2.7
Classifier: Programming Language :: Python :: 3
Classifier: Programming Language :: Python :: 3.4
Classifier: Programming Language :: Python :: 3.5
Classifier: Programming Language :: Python :: 3.6
Classifier: Programming Language :: Python :: 3.7
Classifier: Programming Language :: Python :: 3.8
Classifier: Programming Language :: Python :: 3.9
Classifier: Programming Language :: Python :: Implementation :: CPython
Classifier: Programming Language :: Python :: Implementation :: PyPy
Classifier: Topic :: Software Development :: Libraries :: Python Modules
License-File: LICENSE.txt
